sfisop_tsdatamodel/__init__.py
sfisop_tsdatamodel/metadata.py
sfisop_tsdatamodel/timeseriesdata.py
sfisop_tsdatamodel/tsdata_utils.py
sfisop_tsdatamodel-0.1.3.dist-info/METADATA
sfisop_tsdatamodel-0.1.3.dist-info/WHEEL
sfisop_tsdatamodel-0.1.3.dist-info/RECORD
