Metadata-Version: 2.1
Name: sfisop_tsdatamodel
Version: 0.1.3
Summary: 
Author: Y581515
Author-email: yfessaha@gmail.com
Requires-Python: >=3.10,<4.0.0
Classifier: Programming Language :: Python :: 3
Classifier: Programming Language :: Python :: 3.10
Classifier: Programming Language :: Python :: 3.11
Classifier: Programming Language :: Python :: 3.12
Requires-Dist: pydantic (>=1.10.9,<2.0.0)
Requires-Dist: pytest (>=8.3.2,<9.0.0)
Requires-Dist: typing-extensions (>=4.6.3,<5.0.0)
